multimedia/__init__.py
multimedia/__main__.py
multimedia/config.py
multimedia/database.py
multimedia/main.py
multimedia/models.py
multimedia/scanner.py
multimedia/utils.py
multimedia/video_processor.py
multimedia/routers/__init__.py
multimedia/routers/stream.py
multimedia/routers/tags.py
multimedia/routers/thumbnails.py
multimedia/routers/videos.py
multimedia/static/index.html
multimedia/static/assets/index-BH4tnrIA.css
multimedia/static/assets/index-DUHFgMyD.js
multimedia-0.1.3.dist-info/METADATA
multimedia-0.1.3.dist-info/WHEEL
multimedia-0.1.3.dist-info/entry_points.txt
multimedia-0.1.3.dist-info/licenses/LICENSE
multimedia-0.1.3.dist-info/RECORD
