Metadata-Version: 2.4
Name: multimedia
Version: 0.1.3
Summary: Video indexing and playback web service
Project-URL: Homepage, https://github.com/ozkatz/multimedia
Project-URL: Repository, https://github.com/ozkatz/multimedia
License-Expression: Apache-2.0
License-File: LICENSE
Keywords: fastapi,media,streaming,video
Classifier: Development Status :: 4 - Beta
Classifier: Framework :: FastAPI
Classifier: License :: OSI Approved :: Apache Software License
Classifier: Programming Language :: Python :: 3
Classifier: Programming Language :: Python :: 3.10
Classifier: Programming Language :: Python :: 3.11
Classifier: Programming Language :: Python :: 3.12
Requires-Python: >=3.10
Requires-Dist: aiosqlite>=0.19.0
Requires-Dist: fastapi>=0.109.0
Requires-Dist: ffprobe>=0.5
Requires-Dist: pydantic-settings>=2.0.0
Requires-Dist: pydantic>=2.0.0
Requires-Dist: uvicorn[standard]>=0.27.0
